Workbook

Sheet CFO_Summary
A1: ERG S.A. — CFO ANALYSIS
A2: Producent folii PE | 2023 – 2025 | tys. zł
A4: KEY METRICS | B4: 2023 | C4: 2024 | D4: 2025
A5: EBITDA | B5: ='01_Source_Data'!B10 | C5: ='01_Source_Data'!C10 | D5: ='01_Source_Data'!D10
A6: CFO | B6: ='01_Source_Data'!B23 | C6: ='01_Source_Data'!C23 | D6: ='01_Source_Data'!D23
A7: CCC (dni) | B7: n/d | C7: =CCC!C6 | D7: =CCC!D6
A8: Cash Flow Sales | B8: n/d | C8: =Cash_Flow_Sales!C5 | D8: =Cash_Flow_Sales!D5
A10: WHAT DRIVES CASH
A11: 2024 — Problemy
A12: − Revenue decline −22%
A13: − Inventory build-up ↑ DIO 82 dni
A14: − Payables fell ↓ DPO 45 dni
A16: 2025 — Co pomogło
A17: + Inventory reduction ↓ DIO 73 dni (+1 463)
A18: + Payables increase ↑ DPO 56 dni (+1 922)
A19: + Lower raw material prices (PE effect)
A20: ⚠ Receivables increase ↑ DSO 51 dni (−1 195)
A21: ⚠ No structural margin improvement
A23: KEY MESSAGE
A24: ERG improved cash flow in 2025 through working capital optimization and lower raw material prices — not through structural margin recovery. CCC improved from 83 to 68 days. However, COGS% continues to rise (86.4%) and DSO is growing (51 days). The business generates cash, but does not yet earn it.

Sheet EBITDA_CFO
A1: EBITDA vs CFO — Gotówkowa siła operacyjna
A2: tys. zł | Amortyzacja jest kluczowa dla producenta: maszyny, linie produkcyjne
C3: 2023 | D3: 2024 | E3: 2025
A4: EBIT | C4: ='01_Source_Data'!B8 | D4: ='01_Source_Data'!C8 | E4: ='01_Source_Data'!D8
A5: + Amortyzacja (D&A) | C5: ='01_Source_Data'!B9 | D5: ='01_Source_Data'!C9 | E5: ='01_Source_Data'!D9
A6: EBITDA | C6: ='01_Source_Data'!B10 | D6: ='01_Source_Data'!C10 | E6: ='01_Source_Data'!D10
A7: CFO | C7: ='01_Source_Data'!B23 | D7: ='01_Source_Data'!C23 | E7: ='01_Source_Data'!D23
A8: CFO / EBITDA | C8: =IF(C6=0,"n/d",C7/C6) | D8: =IF(D6=0,"n/d",D7/D6) | E8: =IF(E6=0,"n/d",E7/E6)
A9: Zysk netto | C9: ='01_Source_Data'!B11 | D9: ='01_Source_Data'!C11 | E9: ='01_Source_Data'!D11
A10: CCR (CFO / Zysk netto) | C10: =IF('01_Source_Data'!B11<=0,"n/d",'01_Source_Data'!B23/'01_Source_Data'!B11) | D10: n/d | E10: n/d
A12: INSIGHT · 2023: CFO/EBITDA = 0.72x — dobra konwersja. 2024: EBITDA dodatnia (+3 828), ale CFO ujemny (−1 128): KON pochłonął gotówkę. 2025: CFO > EBITDA (1.37x) — uwolnienie KON, nie poprawa marży. CCR nie stosujemy gdy zysk netto ≤ 0 (2024, 2025).

Sheet Working_Capital
A1: WORKING CAPITAL — Gdzie siedzi gotówka?
A2: tys. zł | KON = Należności + Zapasy − Zobowiązania handlowe
C3: 2024 | D3: 2025
A4: Należności handlowe | C4: ='01_Source_Data'!C15 | D4: ='01_Source_Data'!D15
A5: Zapasy | C5: ='01_Source_Data'!C14 | D5: ='01_Source_Data'!D14
A6: − Zobowiązania handlowe | C6: ='01_Source_Data'!C20 | D6: ='01_Source_Data'!D20
A7: KON | C7: =C4+C5-C6 | D7: =D4+D5-D6
A9: ΔKON (vs rok poprzedni) | C9: =C7-F99 | D9: =D7-C7
A11: INSIGHT · 2024: KON wzrósł do 15 629 (+5 223 vs 2023). Główny driver: zapasy +5 046. Gotówka zamrożona w magazynie. 2025: KON spada do 13 439 (−2 190). Zapasy ↓ +1 463, DPO ↑ +1 922, DSO ↓ −1 195. Uwolnienie częściowo efektem tańszego surowca PE, nie tylko zarządzania.
F99: ='01_Source_Data'!B15+'01_Source_Data'!B14-'01_Source_Data'!B20

Sheet Cash_Flow_Sales
A1: CASH FLOW SALES — Mechanizm gotówki ze sprzedaży
A2: tys. zł | Wzór: CFS = EBIT − ΔKON
C3: 2024 | D3: 2025
A4: EBIT | C4: ='01_Source_Data'!C8 | D4: ='01_Source_Data'!D8
A5: − ΔKON (zmiana kapitału obrotowego) | C5: =Working_Capital!C8 | D5: =Working_Capital!D8
A6: CASH FLOW SALES | C6: =C4-C5 | D6: =D4-D5
A8: CFS Margin (CFS / Przychody) | C8: =IF('01_Source_Data'!C5=0,"n/d",C6/'01_Source_Data'!C5) | D8: =IF('01_Source_Data'!D5=0,"n/d",D6/'01_Source_Data'!D5)
A10: 2024 DRIVER | D10: 2025 DRIVER
A11: EBIT: −821 (słaba marża) | D11: EBIT: +552
A12: ΔKON: +5 223 (zapasy ↑) | D12: ΔKON: −2 190 (zapasy ↓ + DPO ↑)
A13: → gotówka zamrożona | D13: → uwolnienie KON
A15: INSIGHT · 2024: mimo tylko −0.8 mln EBIT, Cash Flow Sales wyniósł −6.0 mln. KON pochłonął o 5.2 mln więcej niż EBIT był w stanie wyprodukować. 2025: uwolnienie KON o 2.2 mln + skromny EBIT = CFS +2.7 mln. Poprawa jest realna, ale krucha — bez poprawy marży nie będzie trwała.

Sheet CCC
A1: CASH CONVERSION CYCLE — DSO / DIO / DPO / CCC
A2: dni | Cel: minimalizacja CCC przy zachowaniu relacji z klientami i dostawcami
C3: 2024 | D3: 2025 | E3: Δ 24→25 | F3: Flaga
A4: DSO = Należności / Przychody × 365 | C4: =IF('01_Source_Data'!C5=0,"n/d",'01_Source_Data'!C15/'01_Source_Data'!C5*365) | D4: =IF('01_Source_Data'!D5=0,"n/d",'01_Source_Data'!D15/'01_Source_Data'!D5*365) | E4: =IF(OR(C4="n/d",D4="n/d"),"n/d",D4-C4) | F4: 🔴 | G4: rośnie → ERG finansuje klientów dłużej
A5: DIO = Zapasy / COGS × 365 | C5: =IF('01_Source_Data'!C6=0,"n/d",'01_Source_Data'!C14/'01_Source_Data'!C6*365) | D5: =IF('01_Source_Data'!D6=0,"n/d",'01_Source_Data'!D14/'01_Source_Data'!D6*365) | E5: =IF(OR(C5="n/d",D5="n/d"),"n/d",D5-C5) | F5: 🟢 | G5: spada → mniej gotówki zamrożonej w magazynie
A6: DPO = Zob. handlowe / COGS × 365 | C6: =IF('01_Source_Data'!C6=0,"n/d",'01_Source_Data'!C20/'01_Source_Data'!C6*365) | D6: =IF('01_Source_Data'!D6=0,"n/d",'01_Source_Data'!D20/'01_Source_Data'!D6*365) | E6: =IF(OR(C6="n/d",D6="n/d"),"n/d",D6-C6) | F6: 🟢 | G6: rośnie → dostawcy finansują biznes
A8: CCC = DSO + DIO − DPO | C8: =IF(OR(C4="n/d",C5="n/d",C6="n/d"),"n/d",C4+C5-C6) | D8: =IF(OR(D4="n/d",D5="n/d",D6="n/d"),"n/d",D4+D5-D6) | E8: =IF(OR(C8="n/d",D8="n/d"),"n/d",D8-C8) | F8: 🟢
A10: INSIGHT · CCC 2024 = 83 dni → 2025 = 68 dni (−15 dni). DIO: −9 dni (zapasy częściowo tańsze przez spadek cen PE). DPO: +11 dni (dostawcy finansują więcej). DSO: +5 dni (należy monitorować — ryzyko 2026).

Sheet Profitability
A1: PROFITABILITY — Marże i Trend
A2: tys. zł | YoY = zmiana rok do roku | pp = punkty procentowe
C3: 2023 | D3: 2024 | E3: 2025 | F3: 2024 YoY | G3: 2025 YoY
A4: WARTOŚCI BEZWZGLĘDNE
A5: Przychody | C5: ='01_Source_Data'!B5 | D5: ='01_Source_Data'!C5 | E5: ='01_Source_Data'!D5 | F5: =IF(OR(C5=0,C5=""),"n/d",(D5-C5)/C5) | G5: =IF(OR(D5=0,D5=""),"n/d",(E5-D5)/D5)
A6: COGS | C6: ='01_Source_Data'!B6 | D6: ='01_Source_Data'!C6 | E6: ='01_Source_Data'!D6 | F6: =IF(OR(C6=0,C6=""),"n/d",(D6-C6)/C6) | G6: =IF(OR(D6=0,D6=""),"n/d",(E6-D6)/D6) | H6: Rośnie szybciej niż przychody ❌
A7: EBITDA | C7: ='01_Source_Data'!B10 | D7: ='01_Source_Data'!C10 | E7: ='01_Source_Data'!D10 | F7: =IF(OR(C7=0,C7=""),"n/d",(D7-C7)/C7) | G7: =IF(OR(D7=0,D7=""),"n/d",(E7-D7)/D7) | H7: Kluczowy wskaźnik producenta
A8: EBIT | C8: ='01_Source_Data'!B8 | D8: ='01_Source_Data'!C8 | E8: ='01_Source_Data'!D8 | F8: =IF(OR(C8=0,C8=""),"n/d",(D8-C8)/C8) | G8: =IF(OR(D8=0,D8=""),"n/d",(E8-D8)/D8)
A9: Zysk netto | C9: ='01_Source_Data'!B11 | D9: ='01_Source_Data'!C11 | E9: ='01_Source_Data'!D11 | F9: =IF(OR(C9=0,C9=""),"n/d",(D9-C9)/C9) | G9: =IF(OR(D9=0,D9=""),"n/d",(E9-D9)/D9) | H9: Blisko zera 2024–2025
A11: MARŻE (% PRZYCHODÓW)
A12: COGS % | C12: =IF('01_Source_Data'!B5=0,"n/d",'01_Source_Data'!B6/'01_Source_Data'!B5) | D12: =IF('01_Source_Data'!C5=0,"n/d",'01_Source_Data'!C6/'01_Source_Data'!C5) | E12: =IF('01_Source_Data'!D5=0,"n/d",'01_Source_Data'!D6/'01_Source_Data'!D5) | F12: =IF(OR(C12="n/d",D12="n/d"),"n/d",D12-C12) | G12: =IF(OR(D12="n/d",E12="n/d"),"n/d",E12-D12) | H12: 80.7% → 85.9% → 86.4% ↑↑ Główne ryzyko
A13: EBITDA % | C13: =IF('01_Source_Data'!B5=0,"n/d",'01_Source_Data'!B10/'01_Source_Data'!B5) | D13: =IF('01_Source_Data'!C5=0,"n/d",'01_Source_Data'!C10/'01_Source_Data'!C5) | E13: =IF('01_Source_Data'!D5=0,"n/d",'01_Source_Data'!D10/'01_Source_Data'!D5) | F13: =IF(OR(C13="n/d",D13="n/d"),"n/d",D13-C13) | G13: =IF(OR(D13="n/d",E13="n/d"),"n/d",E13-D13) | H13: 9.3% → 5.2% → 6.8% Częściowe odbicie
A14: EBIT % | C14: =IF('01_Source_Data'!B5=0,"n/d",'01_Source_Data'!B8/'01_Source_Data'!B5) | D14: =IF('01_Source_Data'!C5=0,"n/d",'01_Source_Data'!C8/'01_Source_Data'!C5) | E14: =IF('01_Source_Data'!D5=0,"n/d",'01_Source_Data'!D8/'01_Source_Data'!D5) | F14: =IF(OR(C14="n/d",D14="n/d"),"n/d",D14-C14) | G14: =IF(OR(D14="n/d",E14="n/d"),"n/d",E14-D14) | H14: 4.2% → −1.1% → +0.7%
A15: Net margin | C15: =IF('01_Source_Data'!B5=0,"n/d",'01_Source_Data'!B11/'01_Source_Data'!B5) | D15: =IF('01_Source_Data'!C5=0,"n/d",'01_Source_Data'!C11/'01_Source_Data'!C5) | E15: =IF('01_Source_Data'!D5=0,"n/d",'01_Source_Data'!D11/'01_Source_Data'!D5) | F15: =IF(OR(C15="n/d",D15="n/d"),"n/d",D15-C15) | G15: =IF(OR(D15="n/d",E15="n/d"),"n/d",E15-D15) | H15: 3.4% → −0.9% → −0.1% Brak rentowności
A17: INSIGHT · Operating leverage zadziałał negatywnie w 2024: przychody −22%, EBITDA −56%. Koszty nie dostosowały się do spadku wolumenów. 2025: wolumen +3.3%, przychody +1.0% → cena/tonę spada. COGS% nadal rośnie. Bez podniesienia cen lub cięcia kosztów poprawa jest tymczasowa.

Sheet Liquidity_Debt
A1: LIQUIDITY & DEBT — Bezpieczeństwo finansowe
A2: Wnioski: ERG nie ma problemu finansowego. Problem jest operacyjny.
C3: 2023 | D3: 2024 | E3: 2025 | F3: Wzorzec
A4: PŁYNNOŚĆ
A5: Current Ratio | C5: ='01_Source_Data'!B13/'01_Source_Data'!B19 | D5: ='01_Source_Data'!C13/'01_Source_Data'!C19 | E5: ='01_Source_Data'!D13/'01_Source_Data'!D19 | F5: >1.5x
A6: Quick Ratio | C6: =('01_Source_Data'!B13-'01_Source_Data'!B14)/'01_Source_Data'!B19 | D6: =('01_Source_Data'!C13-'01_Source_Data'!C14)/'01_Source_Data'!C19 | E6: =('01_Source_Data'!D13-'01_Source_Data'!D14)/'01_Source_Data'!D19 | F6: >1.0x
A7: Cash Ratio | C7: =IF('01_Source_Data'!B16="","n/d",'01_Source_Data'!B16/'01_Source_Data'!B19) | D7: =IF('01_Source_Data'!C16="","n/d",'01_Source_Data'!C16/'01_Source_Data'!C19) | E7: =IF('01_Source_Data'!D16="","n/d",'01_Source_Data'!D16/'01_Source_Data'!D19) | F7: >0.2x
A9: ZADŁUŻENIE
A10: Debt to Equity | C10: ='01_Source_Data'!B18/'01_Source_Data'!B21 | D10: ='01_Source_Data'!C18/'01_Source_Data'!C21 | E10: ='01_Source_Data'!D18/'01_Source_Data'!D21 | F10: <1.0x
A11: Debt to Assets | C11: ='01_Source_Data'!B18/'01_Source_Data'!B17 | D11: ='01_Source_Data'!C18/'01_Source_Data'!C17 | E11: ='01_Source_Data'!D18/'01_Source_Data'!D17 | F11: <0.6
A13: RENTOWNOŚĆ
A14: ROA | C14: ='01_Source_Data'!B11/'01_Source_Data'!B17 | D14: ='01_Source_Data'!C11/'01_Source_Data'!C17 | E14: ='01_Source_Data'!D11/'01_Source_Data'!D17 | F14: >5%
A15: ROE | C15: ='01_Source_Data'!B11/'01_Source_Data'!B21 | D15: ='01_Source_Data'!C11/'01_Source_Data'!C21 | E15: ='01_Source_Data'!D11/'01_Source_Data'!D21 | F15: >10%
A16: Net margin | C16: ='01_Source_Data'!B11/'01_Source_Data'!B5 | D16: ='01_Source_Data'!C11/'01_Source_Data'!C5 | E16: ='01_Source_Data'!D11/'01_Source_Data'!D5 | F16: >3%
A18: INSIGHT · Current Ratio rosnący (1.48→1.79) ✅. Quick Ratio 2024 = 0.68 ❌ — płynność zależy od sprzedaży zapasów. D/E = 0.69, D/A = 0.41 — brak presji zadłużeniowej ✅. Problem ERG jest OPERACYJNY (marża, KON), nie FINANSOWY (dług).

Sheet CFO_Driver_Bridge
A1: CFO DRIVER BRIDGE — EBITDA → CFO
A2: tys. zł | Mechanizm: skąd pochodzi gotówka operacyjna
C3: 2024 | D3: 2025
A4: EBITDA | C4: ='01_Source_Data'!C10 | D4: ='01_Source_Data'!D10 | E4: Gotówkowa siła operacyjna
A5: + Δ Zapasy (spadek = gotówka) | C5: =-('01_Source_Data'!C14-'01_Source_Data'!B14) | D5: =-('01_Source_Data'!D14-'01_Source_Data'!C14) | E5: 2024: zapasy ↑ = absorpcja ❌ / 2025: zapasy ↓ = uwolnienie ✅
A6: + Δ Należności (spadek = gotówka) | C6: =-('01_Source_Data'!C15-'01_Source_Data'!B15) | D6: =-('01_Source_Data'!D15-'01_Source_Data'!C15) | E6: 2024: należności ↓ = ok ✅ / 2025: należności ↑ = absorpcja ❌
A7: + Δ Zob. handlowe (wzrost = gotówka) | C7: ='01_Source_Data'!C20-'01_Source_Data'!B20 | D7: ='01_Source_Data'!D20-'01_Source_Data'!C20 | E7: 2024: zobowiązania ↓ = absorpcja ❌ / 2025: zobowiązania ↑ = finansowanie ✅
A8: Inne korekty (podatek, odsetki, inne KON) | C8: ='01_Source_Data'!C23-(C4+C5+C6+C7) | D8: ='01_Source_Data'!D23-(D4+D5+D6+D7) | E8: Residual: podatek CIT, odsetki, pozostałe zmiany KON
A10: CFO | C10: ='01_Source_Data'!C23 | D10: ='01_Source_Data'!D23
A12: INSIGHT · 2025 Bridge: EBITDA 5 069 + zapasy +1 463 + należności −1 195 + zobowiązania +1 922 + inne ≈ CFO 6 949. CFO pochodzi z KON (ok. +2 190 net) + EBITDA (5 069). Poprawa jest realna, ale nie wynika z poprawy marży — efekt KON + tańszy surowiec PE.

Sheet CFO_Storytelling
A1: CFO STORYTELLING — Liczby vs Narracja zarządu
A3: Obszar | C3: Co mówią liczby | D3: Co mówi zarząd | E3: Wniosek CFO
A4: Sprzedaż | C4: 94,3→73,7→74,5 mln. 2025: wolumen +3.3%, wartość +1.0% → cena/t spada. | D4: Pogorszenie koniunktury 2024. Stabilizacja 2025. Bez analizy cenowej. | E4: ✅ Spójne. ⚠️ Brak wyjaśnienia presji cenowej. Efekt: więcej ton, mniej pieniędzy/t.
A5: Marża | C5: COGS%: 80.7%→85.9%→86.4%. EBITDA: 8.7→3.8→5.1 mln (−56%→+32%). | D5: Presja surowcowa (PE, energia). Bez analizy operating leverage. | E5: ❌ Koszty nie dostosowały się do −22% sprzedaży. Operating leverage zadziałał negatywnie.
A6: Zapasy / DIO | C6: Zapasy: 9.3→14.3→12.8 mln. DIO: 44→82→73 dni. Wzrost 2024 = driver CFO <0. | D6: Brak wyjaśnienia wzrostu i redukcji zapasów w raporcie. | E6: ❌ Największy brak raportu. CFO: 5 mln zamrożone w 2024. 2025: redukcja = KON + efekt cen PE.
A7: Należności / DSO | C7: Należności: 12.6→9.2→10.4 mln. DSO: n/d→46→51 dni. Rośnie. | D7: Brak komentarza. | E7: ⚠️ ERG finansuje klientów dłużej. DSO wzrostowy = ryzyko CFO 2026.
A8: Zobowiązania / DPO | C8: Zob. handlowe: 11.5→7.9→9.8 mln. DPO: n/d→45→56 dni. Wzrost 2025. | D8: Brak komentarza. | E8: ✅ DPO +11 dni = dostawcy finansują +1.9 mln gotówki. Jedyny czysty pozytyw KON.
A9: CFO vs EBITDA | C9: CFO: 6.3→−1.1→6.9 mln. EBITDA: 8.7→3.8→5.1. CFO/EBITDA: 0.72→n/d→1.37x. | D9: Ogólny opis wyników. Bez rozbicia CFO na KON vs EBITDA. | E9: ✅ 2025: CFO > EBITDA = uwolnienie KON. ❌ Nie wynika z marży. Model żyje na KON.
A10: Cash Flow Sales | C10: CFS 2024 = −6 044. CFS 2025 = +2 742. Driver: ΔKON, nie EBIT. | D10: Brak jakiegokolwiek odniesienia do mechanizmu Cash Flow. | E10: ❌ 2024: KON pochłonął 5.2 mln → CFS ujemny. ✅ 2025: uwolnienie KON → CFS +2.7 mln. Krucha poprawa.
A11: Zadłużenie | C11: D/E: 0.79→0.69. D/A: 0.44→0.41. Brak presji. | D11: Brak sygnałów problemów z długiem. | E11: ✅ Bilans bezpieczny. Firma ma czas. Problem jest operacyjny, nie finansowy.

Sheet Red_Flags
A1: RED FLAGS — Perspektywa CFO
A3: 🔴 | B3: Rosnący COGS% (80.7% → 86.4%) | C3: Koszty produkcji rosną szybciej niż sprzedaż. Bez korekty marża znika. | D3: Profitability
A4: 🔴 | B4: CFO zależny od KON, nie od marży | C4: CFS 2024=−6 044, 2025=+2 742. Gotówka pochodzi z rotacji KON, nie z zysku. | D4: Cash_Flow_Sales
A5: 🔴 | B5: DSO rośnie (46 → 51 dni) | C5: ERG finansuje klientów coraz dłużej. Ryzyko dla CFO 2026. | D5: CCC
A6: 🔴 | B6: Brak rentowności netto 2024–2025 | C6: Net margin: −0.9% → −0.1%. Bez wzrostu marży nie ma organicznej poprawy. | D6: Liquidity_Debt
A7: 🔴 | B7: Wrażliwość na ceny PE i energii | C7: COGS% rośnie mimo stabilizacji sprzedaży → brak elastyczności kosztowej. | D7: Profitability
A8: 🟡 | B8: Cash Ratio 0.03 → 0.13 (bardzo niski) | C8: Firma nie trzyma gotówki. Działa na obrocie KON. Brak bufora. | D8: Liquidity_Debt
A9: 🟡 | B9: Quick Ratio 0.68 w 2024 | C9: Płynność zależy od sprzedaży zapasów. Poprawa 2025 do 0.87. | D9: Liquidity_Debt
A10: 🟡 | B10: Zmiana prezentacji RZiS 2025 | C10: Układ porównawczy zamiast kalkulacyjnego — utrudnia śledzenie COGS. | D10: Source_Data

Sheet Data_Requests
A1: DATA REQUESTS — Czego brakuje i o co pytać spółkę
A3: 1 | B3: AR Aging (0–30 / 31–60 / 60+ dni) | C3: DSO=51 dni — ile % jest przeterminowane? Jakość należności. | D3: CCC, Red_Flags
A4: 2 | B4: AP Aging | C4: Rzeczywiste DPO i ryzyko utraty rabatów dostawców. | D4: CCC
A5: 3 | B5: Inventory Aging | C5: Czy wzrost 2024 to surowce czy wyroby gotowe? Ryzyko odpisów. | D5: Working_Capital
A6: 4 | B6: Rozbicie COGS: PE / energia / praca | C6: Identyfikacja głównego drivera wzrostu COGS%. | D6: Profitability
A7: 5 | B7: Rozbicie CFO: EBITDA / KON / inne | C7: Weryfikacja ile z CFO 6,9 mln pochodzi z KON, a ile z EBITDA. | D7: CFO_Driver_Bridge
A8: 6 | B8: Harmonogram zadłużenia | C8: Kiedy zapadają zobowiązania finansowe? | D8: Liquidity_Debt
A9: 7 | B9: Koszty odsetek | C9: Brak Interest Coverage Ratio. Ile kosztuje dług? | D9: Liquidity_Debt
A10: 8 | B10: Warunki płatności klientów | C10: Wyjaśnienie wzrostu DSO 46→51 dni. | D10: CCC

Sheet Flags
A1: Metric | B1: Category | C1: 2024 | D1: 2025 | E1: Change | F1: Flag | G1: Insight
A2: DSO | B2: CCC | C2: =CCC!C3 | D2: =CCC!D3 | E2: =IF(OR(CCC!C3="n/d",CCC!D3="n/d"),"n/d",CCC!D3-CCC!C3) | F2: NEGATIVE | G2: DSO rising — ERG finances clients longer. Risk for 2026 CFO.
A3: DIO | B3: CCC | C3: =CCC!C4 | D3: =CCC!D4 | E3: =IF(OR(CCC!C4="n/d",CCC!D4="n/d"),"n/d",CCC!D4-CCC!C4) | F3: POSITIVE | G3: Inventory reduction — part operational, part lower PE prices.
A4: DPO | B4: CCC | C4: =CCC!C5 | D4: =CCC!D5 | E4: =IF(OR(CCC!C5="n/d",CCC!D5="n/d"),"n/d",CCC!D5-CCC!C5) | F4: POSITIVE | G4: Suppliers finance more — positive for CFO.
A5: CCC | B5: CCC | C5: =CCC!C6 | D5: =CCC!D6 | E5: =IF(OR(CCC!C6="n/d",CCC!D6="n/d"),"n/d",CCC!D6-CCC!C6) | F5: POSITIVE | G5: CCC improved 83→68 days. Working capital cycle faster.
A6: EBITDA | B6: Profitability | C6: ='01_Source_Data'!C10 | D6: ='01_Source_Data'!D10 | E6: =IF('01_Source_Data'!C10=0,"n/d",('01_Source_Data'!D10-'01_Source_Data'!C10)/ABS('01_Source_Data'!C10)) | F6: POSITIVE | G6: EBITDA recovering. Still below 2023 level.
A7: EBIT | B7: Profitability | C7: ='01_Source_Data'!C8 | D7: ='01_Source_Data'!D8 | E7: n/d | F7: CAUTION | G7: EBIT near zero. No structural margin recovery yet.
A8: Net_Income | B8: Profitability | C8: ='01_Source_Data'!C11 | D8: ='01_Source_Data'!D11 | E8: n/d | F8: NEGATIVE | G8: Net loss 2024. Near-zero 2025. No retained earnings.
A9: COGS_pct | B9: Profitability | C9: ='01_Source_Data'!C6/'01_Source_Data'!C5 | D9: ='01_Source_Data'!D6/'01_Source_Data'!D5 | E9: ='01_Source_Data'!D6/'01_Source_Data'!D5-'01_Source_Data'!C6/'01_Source_Data'!C5 | F9: NEGATIVE | G9: COGS% rising to 86.4%. Cost structure not adjusted.
A10: EBITDA_margin | B10: Profitability | C10: ='01_Source_Data'!C10/'01_Source_Data'!C5 | D10: ='01_Source_Data'!D10/'01_Source_Data'!D5 | E10: ='01_Source_Data'!D10/'01_Source_Data'!D5-'01_Source_Data'!C10/'01_Source_Data'!C5 | F10: POSITIVE | G10: EBITDA margin recovering: 5.2%→6.8%. Still below 9.3% (2023).
A11: CFO | B11: Cash | C11: ='01_Source_Data'!C23 | D11: ='01_Source_Data'!D23 | E11: n/d | F11: POSITIVE | G11: CFO strongly positive in 2025. Driven by KON release.
A12: CFS | B12: Cash_Flow_Sales | C12: =Cash_Flow_Sales!C5 | D12: =Cash_Flow_Sales!D5 | E12: n/d | F12: POSITIVE | G12: CFS improved from -6 044 to +2 742. KON release is the driver.
A13: CFO_EBITDA | B13: Cash | C13: =EBITDA_CFO!C7 | D13: =EBITDA_CFO!D7 | E13: n/d | F13: POSITIVE | G13: 2025: CFO/EBITDA=1.37x. KON contributed ~2 190 above EBITDA.
A14: Current_Ratio | B14: Liquidity | C14: ='01_Source_Data'!C13/'01_Source_Data'!C19 | D14: ='01_Source_Data'!D13/'01_Source_Data'!D19 | E14: ='01_Source_Data'!D13/'01_Source_Data'!D19-'01_Source_Data'!C13/'01_Source_Data'!C19 | F14: POSITIVE | G14: Current ratio improving 1.48→1.79. No liquidity crisis.
A15: Debt_Equity | B15: Liquidity | C15: ='01_Source_Data'!C18/'01_Source_Data'!C21 | D15: ='01_Source_Data'!D18/'01_Source_Data'!D21 | E15: ='01_Source_Data'!D18/'01_Source_Data'!D21-'01_Source_Data'!C18/'01_Source_Data'!C21 | F15: POSITIVE | G15: D/E falling 0.72→0.69. No debt pressure.

Sheet Story_Data
A1: section | B1: metric | C1: unit | D1: val_2023 | E1: val_2024 | F1: val_2025 | G1: yoy_2024 | H1: yoy_2025 | I1: flag | J1: insight
A2: Revenue | B2: Sales_PLN_000 | C2: PLN_thousands | D2: ='01_Source_Data'!B5 | E2: ='01_Source_Data'!C5 | F2: ='01_Source_Data'!D5 | G2: =IF(OR(D2=0,D2=""),"n/d",(E2-D2)/ABS(D2)) | H2: =IF(OR(E2=0,E2=""),"n/d",(F2-E2)/ABS(E2)) | I2: CAUTION | J2: Revenue declined 22% in 2024. Flat in 2025 but volume +3.3% with lower unit prices.
A3: Revenue | B3: COGS_PLN_000 | C3: PLN_thousands | D3: ='01_Source_Data'!B6 | E3: ='01_Source_Data'!C6 | F3: ='01_Source_Data'!D6 | G3: =IF(OR(D3=0,D3=""),"n/d",(E3-D3)/ABS(D3)) | H3: =IF(OR(E3=0,E3=""),"n/d",(F3-E3)/ABS(E3)) | I3: NEGATIVE | J3: COGS declining slower than revenue — cost structure not elastic.
A4: Profitability | B4: EBITDA_PLN_000 | C4: PLN_thousands | D4: ='01_Source_Data'!B10 | E4: ='01_Source_Data'!C10 | F4: ='01_Source_Data'!D10 | G4: =IF(OR(D4=0,D4=""),"n/d",(E4-D4)/ABS(D4)) | H4: =IF(OR(E4=0,E4=""),"n/d",(F4-E4)/ABS(E4)) | I4: CAUTION | J4: EBITDA dropped 56% in 2024. Partial recovery +32% in 2025. Still below 2023.
A5: Profitability | B5: EBIT_PLN_000 | C5: PLN_thousands | D5: ='01_Source_Data'!B8 | E5: ='01_Source_Data'!C8 | F5: ='01_Source_Data'!D8 | G5: =IF(OR(D5=0,D5=""),"n/d",(E5-D5)/ABS(D5)) | H5: =IF(OR(E5=0,E5=""),"n/d",(F5-E5)/ABS(E5)) | I5: CAUTION | J5: EBIT negative 2024. Near-zero 2025. Margin recovery slow.
A6: Profitability | B6: Net_Income_PLN_000 | C6: PLN_thousands | D6: ='01_Source_Data'!B11 | E6: ='01_Source_Data'!C11 | F6: ='01_Source_Data'!D11 | G6: =IF(OR(D6=0,D6=""),"n/d",(E6-D6)/ABS(D6)) | H6: =IF(OR(E6=0,E6=""),"n/d",(F6-E6)/ABS(E6)) | I6: NEGATIVE | J6: Net loss in 2024 and 2025. No structural profitability.
A7: Profitability | B7: COGS_pct | C7: percent | D7: ='01_Source_Data'!B6/'01_Source_Data'!B5 | E7: ='01_Source_Data'!C6/'01_Source_Data'!C5 | F7: ='01_Source_Data'!D6/'01_Source_Data'!D5 | G7: =IF(OR(D7=0,D7=""),"n/d",(E7-D7)/ABS(D7)) | H7: =IF(OR(E7=0,E7=""),"n/d",(F7-E7)/ABS(E7)) | I7: NEGATIVE | J7: COGS% rising 80.7% to 86.4%. Key structural risk.
A8: Profitability | B8: EBITDA_margin | C8: percent | D8: ='01_Source_Data'!B10/'01_Source_Data'!B5 | E8: ='01_Source_Data'!C10/'01_Source_Data'!C5 | F8: ='01_Source_Data'!D10/'01_Source_Data'!D5 | G8: =IF(OR(D8=0,D8=""),"n/d",(E8-D8)/ABS(D8)) | H8: =IF(OR(E8=0,E8=""),"n/d",(F8-E8)/ABS(E8)) | I8: CAUTION | J8: EBITDA margin: 9.3% to 5.2% to 6.8%. Recovering but not back to 2023.
A9: Working_Capital | B9: Receivables_PLN_000 | C9: PLN_thousands | D9: ='01_Source_Data'!B15 | E9: ='01_Source_Data'!C15 | F9: ='01_Source_Data'!D15 | G9: =IF(OR(D9=0,D9=""),"n/d",(E9-D9)/ABS(D9)) | H9: =IF(OR(E9=0,E9=""),"n/d",(F9-E9)/ABS(E9)) | I9: CAUTION | J9: Receivables fell in 2024 (positive) but rising in 2025. DSO growing.
A10: Working_Capital | B10: Inventory_PLN_000 | C10: PLN_thousands | D10: ='01_Source_Data'!B14 | E10: ='01_Source_Data'!C14 | F10: ='01_Source_Data'!D14 | G10: =IF(OR(D10=0,D10=""),"n/d",(E10-D10)/ABS(D10)) | H10: =IF(OR(E10=0,E10=""),"n/d",(F10-E10)/ABS(E10)) | I10: NEGATIVE | J10: Inventory jumped to 14 304 in 2024 — main driver of negative CFO.
A11: Working_Capital | B11: Payables_PLN_000 | C11: PLN_thousands | D11: ='01_Source_Data'!B20 | E11: ='01_Source_Data'!C20 | F11: ='01_Source_Data'!D20 | G11: =IF(OR(D11=0,D11=""),"n/d",(E11-D11)/ABS(D11)) | H11: =IF(OR(E11=0,E11=""),"n/d",(F11-E11)/ABS(E11)) | I11: POSITIVE | J11: Payables rising in 2025 — suppliers financing more.
A12: Working_Capital | B12: KON_PLN_000 | C12: PLN_thousands | D12: =Working_Capital!C6 | E12: =Working_Capital!C6 | F12: =Working_Capital!D6 | G12: n/d | H12: n/d | I12: NEGATIVE | J12: KON peaked at 15 629 in 2024 (cash trap). Falling to 13 439 in 2025.
A13: Working_Capital | B13: Delta_KON_PLN_000 | C13: PLN_thousands | D13: n/d | E13: =Working_Capital!C8 | F13: =Working_Capital!D8 | G13: n/d | H13: n/d | I13: POSITIVE | J13: ΔKON: +5 223 in 2024 (absorbing cash), −2 190 in 2025 (releasing cash).
A14: CCC | B14: DSO_days | C14: days | D14: n/d | E14: =CCC!C3 | F14: =CCC!D3 | G14: n/d | H14: n/d | I14: NEGATIVE | J14: DSO rising 46→51 days. Clients paying later.
A15: CCC | B15: DIO_days | C15: days | D15: =IF('01_Source_Data'!B6=0,"n/d",'01_Source_Data'!B14/'01_Source_Data'!B6*365) | E15: =CCC!C4 | F15: =CCC!D4 | G15: n/d | H15: n/d | I15: POSITIVE | J15: DIO improved 82→73 days. Partially price effect (cheaper PE).
A16: CCC | B16: DPO_days | C16: days | D16: =IF('01_Source_Data'!B6=0,"n/d",'01_Source_Data'!B20/'01_Source_Data'!B6*365) | E16: =CCC!C5 | F16: =CCC!D5 | G16: n/d | H16: n/d | I16: POSITIVE | J16: DPO improved 45→56 days. Suppliers financing more.
A17: CCC | B17: CCC_days | C17: days | D17: n/d | E17: =CCC!C6 | F17: =CCC!D6 | G17: n/d | H17: n/d | I17: POSITIVE | J17: CCC improved 83→68 days. Working capital cycle faster.
A18: Cash_Flow | B18: CFO_PLN_000 | C18: PLN_thousands | D18: ='01_Source_Data'!B23 | E18: ='01_Source_Data'!C23 | F18: ='01_Source_Data'!D23 | G18: =IF(OR(D18=0,D18=""),"n/d",(E18-D18)/ABS(D18)) | H18: =IF(OR(E18=0,E18=""),"n/d",(F18-E18)/ABS(E18)) | I18: POSITIVE | J18: CFO: 6 260 → −1 128 → 6 949. Volatile — driven by working capital, not margin.
A19: Cash_Flow | B19: CFS_PLN_000 | C19: PLN_thousands | D19: n/d | E19: =Cash_Flow_Sales!C5 | F19: =Cash_Flow_Sales!D5 | G19: n/d | H19: n/d | I19: POSITIVE | J19: CFS: −6 044 → +2 742. KON release drove improvement, not EBIT.
A20: Cash_Flow | B20: CFO_EBITDA_ratio | C20: ratio | D20: =EBITDA_CFO!C7 | E20: n/d | F20: =EBITDA_CFO!E7 | G20: n/d | H20: n/d | I20: POSITIVE | J20: CFO/EBITDA: 0.72x (2023) → n/d (2024 negative) → 1.37x (2025).
A21: Liquidity | B21: Current_Ratio | C21: ratio | D21: ='01_Source_Data'!B13/'01_Source_Data'!B19 | E21: ='01_Source_Data'!C13/'01_Source_Data'!C19 | F21: ='01_Source_Data'!D13/'01_Source_Data'!D19 | G21: =IF(OR(D21=0,D21=""),"n/d",(E21-D21)/ABS(D21)) | H21: =IF(OR(E21=0,E21=""),"n/d",(F21-E21)/ABS(E21)) | I21: POSITIVE | J21: Current ratio improving 1.48→1.79. No liquidity crisis.
A22: Debt | B22: Debt_Equity | C22: ratio | D22: ='01_Source_Data'!B18/'01_Source_Data'!B21 | E22: ='01_Source_Data'!C18/'01_Source_Data'!C21 | F22: ='01_Source_Data'!D18/'01_Source_Data'!D21 | G22: =IF(OR(D22=0,D22=""),"n/d",(E22-D22)/ABS(D22)) | H22: =IF(OR(E22=0,E22=""),"n/d",(F22-E22)/ABS(E22)) | I22: POSITIVE | J22: D/E falling 0.79→0.69. No debt pressure. Problem is operational.

Sheet 01_Source_Data
A1: SOURCE DATA — ERG S.A. 2023–2025 | tys. zł
A2: Niebieski = dane wejściowe (INP) | Czarny = formuły | To jest arkusz źródłowy — nie edytuj bezpośrednio
A3: Pozycja | B3: 2023 | C3: 2024 | D3: 2025 | E3: Źródło
A4: RACHUNEK WYNIKÓW
A5: Przychody ze sprzedaży | B5: 94272 | C5: 73660 | D5: 74463 | E5: SF RZiS / Spr. zarządu
A6: Koszt własny sprzedaży (COGS) | B6: 76111 | C6: 63287 | D6: 64330 | E6: SF RZiS / Spr. zarządu 2025
A7: Zysk brutto ze sprzedaży | B7: =B5-B6 | C7: =C5-C6 | D7: =D5-D6 | E7: Wzór: Przychody − COGS
A8: Zysk operacyjny (EBIT) | B8: 3975 | C8: -821 | D8: 552 | E8: SF RZiS
A9: Amortyzacja (D&A) | B9: 4745 | C9: 4649 | D9: 4517 | E9: Rachunek przepływów
A10: EBITDA | B10: =B8+B9 | C10: =C8+C9 | D10: =D8+D9 | E10: Wzór: EBIT + D&A
A11: Zysk netto | B11: 3199 | C11: -653 | D11: -67 | E11: SF RZiS
A12: BILANS
A13: Aktywa obrotowe | B13: 23738 | C13: 23916 | D13: 25056 | E13: Bilans
A14: Zapasy | B14: 9258 | C14: 14304 | D14: 12841 | E14: Nota 17
A15: Należności handlowe i pozostałe | B15: 12644 | C15: 9197 | D15: 10392 | E15: Nota 18
A16: Środki pieniężne | C16: 415 | D16: 1823 | E16: Bilans
A17: Aktywa ogółem | B17: 74356 | C17: 70058 | D17: 68514 | E17: Bilans
A18: Zobowiązania ogółem | B18: 32944 | C18: 29303 | D18: 27852 | E18: Bilans
A19: Zobowiązania krótkoterminowe | B19: 16020 | C19: 14266 | D19: 14024 | E19: Bilans
A20: Zobowiązania handlowe | B20: 11496 | C20: 7872 | D20: 9794 | E20: Nota 25
A21: Kapitał własny | B21: 41412 | C21: 40755 | D21: 40662 | E21: Bilans
A22: RACHUNEK PRZEPŁYWÓW
A23: CFO — przepływy z dz. operacyjnej | B23: 6260 | C23: -1128 | D23: 6949 | E23: Rachunek przepływów
